unipropic/__init__.py
unipropic/config_manager.py
unipropic/main.py
unipropic/messages.py
unipropic/webdriver_handlers.py
unipropic-1.1.3.dist-info/LICENSE.txt
unipropic-1.1.3.dist-info/METADATA
unipropic-1.1.3.dist-info/WHEEL
unipropic-1.1.3.dist-info/entry_points.txt
unipropic-1.1.3.dist-info/RECORD
