Metadata-Version: 2.1
Name: unipropic
Version: 1.1.3
Summary: A CLI app that automatically puts a profile image in all your accounts.
Home-page: https://github.com/kutu-dev/unipropic
License: MIT
Keywords: web,utility,automation,profile
Author: kutu-dev
Requires-Python: >=3.11,<4.0
Classifier: Development Status :: 5 - Production/Stable
Classifier: Environment :: Web Environment
Classifier: License :: OSI Approved :: MIT License
Classifier: Operating System :: OS Independent
Classifier: Programming Language :: Python :: 3
Classifier: Programming Language :: Python :: 3.11
Classifier: Topic :: Internet
Classifier: Topic :: Utilities
Requires-Dist: colorama (>=0.4.6,<0.5.0)
Requires-Dist: inquirer (>=3.1.3,<4.0.0)
Requires-Dist: selenium (>=4.8.3,<5.0.0)
Requires-Dist: tomlkit (>=0.11.7,<0.12.0)
Requires-Dist: webdriver-manager (>=3.8.5,<4.0.0)
